pytest_utils/__init__.py
pytest_utils/fixtures.py
pytest_utils/settings.py
pytest_utils/sqlalchemy.py
pytest_utils-0.3.0.dist-info/entry_points.txt
pytest_utils-0.3.0.dist-info/LICENSE.txt
pytest_utils-0.3.0.dist-info/WHEEL
pytest_utils-0.3.0.dist-info/METADATA
pytest_utils-0.3.0.dist-info/RECORD
