Metadata-Version: 2.1
Name: pytest-utils
Version: 0.3.0
Summary: Some helpers for pytest.
Home-page: https://bitbucket.org/p-app/pytest_utils
License: MIT
Author: Vladimir V. Pivovarov
Author-email: admin@p-app.ru
Maintainer: Vladimir V. Pivovarov
Maintainer-email: admin@p-app.ru
Requires-Python: >=3.7,<4.0
Classifier: Development Status :: 4 - Beta
Classifier: Framework :: Pytest
Classifier: Intended Audience :: Developers
Classifier: License :: OSI Approved :: MIT License
Classifier: Programming Language :: Python :: 3
Classifier: Programming Language :: Python :: 3.10
Classifier: Programming Language :: Python :: 3.7
Classifier: Programming Language :: Python :: 3.8
Classifier: Programming Language :: Python :: 3.9
Provides-Extra: sqlalchemy
Requires-Dist: SQLAlchemy (>=1.4.0,<2.0.0); extra == "sqlalchemy"
Requires-Dist: pytest (>=7.0.0,<8.0.0)
Project-URL: Repository, https://bitbucket.org/p-app/pytest_utils
